split_screen_recording_by_monitor/__init__.py
split_screen_recording_by_monitor/core.py
split_screen_recording_by_monitor-0.0.1.dist-info/LICENSE
split_screen_recording_by_monitor-0.0.1.dist-info/METADATA
split_screen_recording_by_monitor-0.0.1.dist-info/WHEEL
split_screen_recording_by_monitor-0.0.1.dist-info/entry_points.txt
split_screen_recording_by_monitor-0.0.1.dist-info/top_level.txt
split_screen_recording_by_monitor-0.0.1.dist-info/RECORD
