Metadata-Version: 2.1
Name: split-screen-recording-by-monitor
Version: 0.0.1
Summary: Split a screen recording video file into N video files, one per monitor
Home-page: https://github.com/tylerlum/split_screen_recording_by_monitor
Author: Tyler Lum
Author-email: tylergwlum@gmail.com
License: UNKNOWN
Keywords: python,screen recording,ffmpeg,split,monitor
Platform: UNKNOWN
Classifier: Intended Audience :: Developers
Classifier: Operating System :: OS Independent
Classifier: Programming Language :: Python :: 3
License-File: LICENSE
Requires-Dist: ffmpeg-python
Requires-Dist: screeninfo
Requires-Dist: tyro
